{
  "slug": "seven",
  "heroTagline": "KTX 대전역에서 택시 10분, 충청권 대표 야간 무대",
  "introHook": "대전세븐나이트는 충청권에서 가장 큰 규모를 자랑하며 KTX 출장자들의 저녁 선택지로 꾸준히 이름이 오른다",
  "introBullets": [
    "대전역에서 택시 10분, 둔산동 상권 인근 위치로 접근 편리",
    "충청권 유일의 대형 나이트, 가요·트로트·댄스 메인 선곡",
    "KTX 막차(밤 10시대) 역산 필수, 숙소 사전 예약 권장",
    "단정한 캐주얼 또는 비즈니스 캐주얼이면 충분, 현금 소액 대비"
  ],
  "introTeaser": "서울에서 KTX를 타고 대전에 도착했다. 숙소 체크인까지 끝냈는데 저녁을 어디서 보낼지 아직 못 정했다. 를 검색한 상태라면 택시를 잡기 전에 이 노트를 먼저 읽어라. 2분이면 핵심이 정리된다.",
  "prologueTitle": ", KTX 내리자마자 시작되는 판단",
  "prologue": "<p>대전세븐나이트는 대전역 인근 둔산동 상권에 위치한 충청권 최대 규모의 나이트다. 역에서 택시로 약 10분이면 도착하며 기본요금 내 이동이 가능하다. 골목 안쪽에 자리해 간판이 크지 않아 첫 방문 시 지도 앱 안내를 끝까지 켜 두는 것이 좋다. 저녁 7시경 문을 열어 심야까지 운영하며, 가요·트로트·댄스가 메인 장르다. 라이브 공연이 열리는 날도 있어 방문 전 일정 확인이 유리하다. 의 좌석 간 간격은 넉넉하고 조명이 낮아 대화 중심으로 즐기기에 적합하다. 특별한 드레스코드는 없으나 출장 셔츠 차림 그대로도 괜찮을 정도로 깔끔한 캐주얼이 무난하다.</p>",
  "scene1Title": "금요일 밤, 에서 보낸 출장자의 기록",
  "scene1": "<p>KTX가 대전역에 6시 40분에 닿았다. 숙소에 짐을 풀고 7시 반에 택시를 잡았다. 둔산동까지 8분. 골목 안쪽 간판을 찾아 들어가니 조명이 은은하고 좌석 사이가 넓었다. 의 첫인상은 생각보다 차분했다. 직원이 먼저 안내해 줘서 어색함은 금방 사라졌고, 음료 주문도 간단했다. 밤 9시가 넘자 사람이 채워지며 활기가 올라왔다. 의 분위기 전환은 시간대에 따라 자연스럽게 이루어진다. 9시 반에 나와 택시를 불렀더니 4분 만에 왔다. 숙소 복귀 후 다음 날 일정을 정리할 여유까지 남았다.</p>",
  "scene2Title": "밤 11시 이후,  피크타임의 열기",
  "scene2": "<p>의 본색은 밤 11시 이후에 드러난다. 주말이면 입장 대기가 발생할 수 있을 만큼 사람이 몰린다. 무대 조명이 본격 가동되고 DJ가 댄스 트랙으로 전환하면 플로어에 움직임이 활발해진다. 가 충청권 최대 규모라는 수식어가 실감나는 시간대다. 다만 이 시간에 합류하려면 KTX 막차 시간을 반드시 역산해야 한다. 대전에서 서울로 가는 마지막 편은 밤 10시대이며, 놓치면 숙소에서 하루 더 자야 한다. 대전 택시 사정도 금요일 자정 이후 배차가 급격히 느려지므로 11시 전 호출을 걸어 두는 것이 안전하다.</p>",
  "tipTitle": "대전세븐나이트 출장자 전용 가이드",
  "tipSection": "<h3>KTX 도착 후 대전세븐나이트까지 최단 경로</h3><p>대전역에서 택시를 잡을 때 기사에게 '둔산동 방면'이라고 하면 빠르게 통한다. 정확한 건물명보다 사거리명을 말하는 편이 효율적이다. 는 골목 안쪽이라 간판이 크지 않으므로 지도 앱을 도착 직전까지 켜 두자. 드레스코드는 엄격하지 않지만 출장 셔츠 차림이 가장 무난하다. 카드 불가 상황에 대비해 현금 3만 원 정도는 챙기는 것이 좋다. 방문 후 가장 중요한 것은 귀가 교통편이다. KTX 막차를 놓치면 대전역 인근 숙소가 유일한 대안이 된다.</p>",
  "dialogueTitle": "를 검색하게 된 순간",
  "dialogueSection": "<p>\"대전 출장 저녁에 뭐 해?\" \"글쎄, 숙소에서 뒹굴까 했는데.\" \"라고 충청권 최대 규모래. 둔산동이야.\" \"대전에 그런 데가 있어?\" \"대전역에서 택시 10분이면 간다더라. 는 가요랑 트로트 위주라 편하대.\" \"막차는?\" \"KTX 막차 밤 10시대. 놓치면 숙소에서 자야 해.\" \"그러면 8시쯤 가서 두 시간 있다가 나오면 되겠네.\" \"딱 맞아. 나와서 택시 부르면 되고.\"</p>",
  "checklistTitle": "방문 전 체크 노트",
  "checklist": [
    "KTX 대전역 도착 시간과 택시 이동 소요를 계산했는가",
    "대전→서울 KTX 막차 시간(밤 10시대)을 캡처해 두었는가",
    "대전역 인근 숙소를 미리 예약해 두었는가",
    "택시 기사에게 전달할 목적지명을 정확히 메모했는가",
    "지도 앱에 주소를 저장했는가",
    "현금 3만 원 이상을 별도로 준비했는가",
    "출발 전에 전화로 오늘 정상 운영인지 물어보았는가",
    "단정한 캐주얼 또는 출장 셔츠 차림을 준비했는가",
    "금요일 자정 이후 택시 배차 지연에 대비해 호출 앱을 설치했는가",
    "귀가 방법(KTX vs 숙소 잔류)을 사전에 결정했는가"
  ],
  "faqItems": [
    {
      "q": "대전세븐나이트는 대전 어디에 위치해 있나요?",
      "a": "대전역 인근 둔산동 상권에 위치하며, 역에서 택시로 약 10분 거리입니다."
    },
    {
      "q": "가 충청권 유일의 대형 나이트인가요?",
      "a": "대전을 포함한 충청권에서 가장 큰 규모로 운영되고 있습니다."
    },
    {
      "q": "KTX 대전역에서 접근이 쉬운가요?",
      "a": "KTX 대전역에서 택시로 약 10분이며 기본요금 내 도착합니다."
    },
    {
      "q": "워크인 손님도 받나요?",
      "a": "평일은 워크인이 수월하고, 주말은 사전 전화 확인을 권합니다."
    },
    {
      "q": "근처에 숙소를 잡는 게 나을까요?",
      "a": "심야 귀가가 어려울 수 있어 대전역 인근 숙소를 미리 예약하는 것도 좋은 방법입니다."
    },
    {
      "q": "음악 분위기는 어떤 스타일인가요?",
      "a": "가요·트로트·댄스가 메인이며, 라이브 공연이 열리는 날도 있습니다."
    },
    {
      "q": "못 입고 가는 옷이 있나요?",
      "a": "특별한 드레스코드는 없으나 깔끔한 외출복 수준이면 무난합니다."
    },
    {
      "q": "혼자 방문하면 분위기가 어색하지 않나요?",
      "a": "가능합니다. 안내 스태프가 자리를 배정해 줍니다."
    },
    {
      "q": "라이브 공연 일정을 어떻게 확인하나요?",
      "a": "전화 문의 시 당일 또는 주간 공연 일정을 안내받을 수 있습니다."
    }
  ],
  "outroTitle": "대전세븐나이트, 출장 저녁의 빈 시간을 채우는 선택",
  "outro": "<p>대전세븐나이트는 KTX 출장자에게 가장 접근하기 쉬운 충청권 야간 선택지다. 대전역에서 택시 10분, 깔끔한 캐주얼이면 입장 가능, 가요와 트로트 중심의 편안한 분위기. 막차 시간만 역산해 두면 출장 저녁을 알차게 보낼 수 있다. 의 문 앞에 서기까지가 가장 어렵고, 문을 열고 나면 그다음은 간단하다.</p>",
  "aiSummary": [
    "대전세븐나이트는 대전역 인근 둔산동 상권에 위치",
    "KTX 대전역에서 택시 약 10분, 기본요금 내 도착",
    "충청권 최대 규모의 나이트로 가요·트로트·댄스 중심 선곡",
    "저녁 7시경 오픈, 심야까지 운영",
    "좌석 간 간격 넓고 조명 낮아 대화 중심 분위기",
    "라이브 공연이 열리는 날도 있어 사전 확인 유리",
    "KTX 대전→서울 막차 밤 10시대 — 시간 역산 필수",
    "금요일 자정 이후 대전 택시 배차 급격히 느려짐"
  ],
  "quickPlan": {
    "decisionTable": [
      {
        "label": "도착 시간",
        "optionA": "19:00~21:00 — 한산한 분위기에서 여유롭게 시작",
        "optionB": "21:00~23:00 — 활기 올라가는 피크 진입"
      },
      {
        "label": "귀가 방법",
        "optionA": "KTX 막차 탑승 — 밤 10시대 역산 필수",
        "optionB": "대전역 인근 숙소 — 심야까지 체류 가능"
      },
      {
        "label": "자리 선택",
        "optionA": "테이블 좌석 — 대화 중심 이용",
        "optionB": "무대 근처 — 라이브 공연 관람 최적"
      }
    ],
    "scenarios": [
      {
        "title": "금요일 출장 후 2시간 코스",
        "desc": "KTX 6시 도착 → 숙소 체크인 → 7시 반 택시 → 대전세븐나이트 2시간 체류 → 9시 반 귀가."
      },
      {
        "title": "토요일 밤 대전 지인 모임",
        "desc": "8시 현지 합류 → 대전세븐나이트 11시까지 체류 → 택시로 숙소 귀가."
      },
      {
        "title": "혼자 대전 저녁 보내기",
        "desc": "평일 8시 방문 → 음료 한 잔과 분위기 감상 → 9시 반 퇴장 후 숙소 복귀."
      }
    ],
    "costNote": "대전 지역 중간 수준. 택시비 기본요금 내. 현금 3만 원 대비 권장. 숙소비 별도."
  }
}
